Metadata-Version: 2.1
Name: lyywinsubscribe
Version: 1.2
Summary: yyjdgui for lyy
Author: lyy
Author-email: 
License: MIT
License-File: LICENSE
